{
  "bookings": [],
  "timeSlots": [
    {
      "id": "slot-1",
      "time": "10:00 AM - 12:00 PM",
      "label": "Morning Show",
      "basePrice": 999
    },
    {
      "id": "slot-2",
      "time": "12:30 PM - 02:30 PM",
      "label": "Matinee Show",
      "basePrice": 999
    },
    {
      "id": "slot-3",
      "time": "03:00 PM - 05:00 PM",
      "label": "Afternoon Vibe",
      "basePrice": 999
    },
    {
      "id": "slot-4",
      "time": "05:30 PM - 07:30 PM",
      "label": "Sunset Vibe",
      "basePrice": 999
    },
    {
      "id": "slot-5",
      "time": "08:00 PM - 10:00 PM",
      "label": "Night Vibe",
      "basePrice": 999
    },
    {
      "id": "slot-6",
      "time": "10:30 PM - 12:30 AM",
      "label": "Midnight Vibe",
      "basePrice": 999
    }
  ],
  "otps": [
    {
      "phone": "+919959338166",
      "hashedOtp": "31529d84a2c2ffe5d2c5399b420ef1010174d27bf6d4ead70928127af0ccf9dd",
      "expiresAt": "2026-07-21T07:31:59.672Z"
    }
  ],
  "foodOrders": [],
  "menuItems": [
    {
      "id": "menu-1",
      "name": "Maggie",
      "price": 70,
      "description": "Hot and delicious instant noodles.",
      "category": "snacks",
      "inStock": true,
      "icon": "🍜"
    },
    {
      "id": "menu-2",
      "name": "Cool drinks",
      "price": 40,
      "description": "Chilled carbonated beverages (per glass).",
      "category": "beverages",
      "inStock": true,
      "icon": "🥤"
    },
    {
      "id": "menu-3",
      "name": "Popcorn",
      "price": 100,
      "description": "Freshly popped warm theater style popcorn.",
      "category": "snacks",
      "inStock": true,
      "icon": "🍿"
    },
    {
      "id": "menu-4",
      "name": "French fries",
      "price": 100,
      "description": "Golden-fried crispy potato strips.",
      "category": "snacks",
      "inStock": true,
      "icon": "🍟"
    },
    {
      "id": "menu-5",
      "name": "Veg nuggets",
      "price": 70,
      "description": "Crispy deep-fried vegetables bites.",
      "category": "snacks",
      "inStock": true,
      "icon": "🧆"
    },
    {
      "id": "menu-6",
      "name": "Chicken nuggets",
      "price": 100,
      "description": "Crispy fried chicken breast bites.",
      "category": "snacks",
      "inStock": true,
      "icon": "🍗"
    },
    {
      "id": "menu-7",
      "name": "Nachos",
      "price": 100,
      "description": "Crunchy tortilla chips with cheese dipping sauce.",
      "category": "snacks",
      "inStock": true,
      "icon": "🌮"
    },
    {
      "id": "menu-8",
      "name": "Sweet corn",
      "price": 70,
      "description": "Steamed butter sweet corn.",
      "category": "snacks",
      "inStock": true,
      "icon": "🌽"
    },
    {
      "id": "menu-9",
      "name": "Burger",
      "price": 100,
      "description": "Delicious patty burger with cheese and fresh sauces.",
      "category": "snacks",
      "inStock": true,
      "icon": "🍔"
    },
    {
      "id": "menu-10",
      "name": "Tea & Coffee",
      "price": 20,
      "description": "Warm and refreshing hot brews.",
      "category": "beverages",
      "inStock": true,
      "icon": "☕"
    },
    {
      "id": "menu-11",
      "name": "Onion rings",
      "price": 150,
      "description": "Crispy fried batter-coated onion rings.",
      "category": "snacks",
      "inStock": true,
      "icon": "🧅"
    },
    {
      "id": "menu-12",
      "name": "Ice cream",
      "price": 40,
      "description": "Scoop of delicious cold ice cream.",
      "category": "desserts",
      "inStock": true,
      "icon": "🍨"
    },
    {
      "name": "Garlic Bread",
      "price": 120,
      "description": "Delicious buttery garlic bread toasted to perfection.",
      "category": "snacks",
      "icon": "🍿",
      "id": "menu-1784527578794",
      "inStock": true
    }
  ]
}